apm_cli/__init__.py
apm_cli/cli.py
apm_cli/config.py
apm_cli/factory.py
apm_cli/version.py
apm_cli/adapters/__init__.py
apm_cli/adapters/client/__init__.py
apm_cli/adapters/client/base.py
apm_cli/adapters/client/codex.py
apm_cli/adapters/client/copilot.py
apm_cli/adapters/client/vscode.py
apm_cli/adapters/package_manager/__init__.py
apm_cli/adapters/package_manager/base.py
apm_cli/adapters/package_manager/default_manager.py
apm_cli/commands/__init__.py
apm_cli/commands/deps.py
apm_cli/compilation/__init__.py
apm_cli/compilation/agents_compiler.py
apm_cli/compilation/claude_formatter.py
apm_cli/compilation/constants.py
apm_cli/compilation/constitution.py
apm_cli/compilation/constitution_block.py
apm_cli/compilation/context_optimizer.py
apm_cli/compilation/distributed_compiler.py
apm_cli/compilation/injector.py
apm_cli/compilation/link_resolver.py
apm_cli/compilation/template_builder.py
apm_cli/core/__init__.py
apm_cli/core/conflict_detector.py
apm_cli/core/docker_args.py
apm_cli/core/operations.py
apm_cli/core/safe_installer.py
apm_cli/core/script_runner.py
apm_cli/core/target_detection.py
apm_cli/core/token_manager.py
apm_cli/deps/__init__.py
apm_cli/deps/aggregator.py
apm_cli/deps/apm_resolver.py
apm_cli/deps/collection_parser.py
apm_cli/deps/dependency_graph.py
apm_cli/deps/github_downloader.py
apm_cli/deps/package_validator.py
apm_cli/deps/verifier.py
apm_cli/integration/__init__.py
apm_cli/integration/agent_integrator.py
apm_cli/integration/command_integrator.py
apm_cli/integration/prompt_integrator.py
apm_cli/integration/skill_integrator.py
apm_cli/integration/skill_transformer.py
apm_cli/integration/utils.py
apm_cli/models/__init__.py
apm_cli/models/apm_package.py
apm_cli/output/__init__.py
apm_cli/output/formatters.py
apm_cli/output/models.py
apm_cli/output/script_formatters.py
apm_cli/primitives/__init__.py
apm_cli/primitives/discovery.py
apm_cli/primitives/models.py
apm_cli/primitives/parser.py
apm_cli/registry/__init__.py
apm_cli/registry/client.py
apm_cli-0.7.0.dist-info/licenses/AUTHORS
apm_cli-0.7.0.dist-info/licenses/LICENSE
apm_cli-0.7.0.dist-info/METADATA
apm_cli-0.7.0.dist-info/WHEEL
apm_cli-0.7.0.dist-info/entry_points.txt
apm_cli-0.7.0.dist-info/top_level.txt
apm_cli-0.7.0.dist-info/RECORD
